src/solana-mev-agent-py/__init__.py
src/solana-mev-agent-py/agents/__init__.py
src/solana-mev-agent-py/agents/aleph.py
src/solana-mev-agent-py/agents/base.py
src/solana-mev-agent-py/agents/main.py
src/solana-mev-agent-py/liquidity/__init__.py
src/solana-mev-agent-py/liquidity/base.py
src/solana-mev-agent-py/liquidity/cexes/__init__.py
src/solana-mev-agent-py/liquidity/cexes/binance.py
src/solana-mev-agent-py/liquidity/jupiter.py
src/solana-mev-agent-py/main.py
src/solana-mev-agent-py/oracles/__init__.py
src/solana-mev-agent-py/oracles/dexscreener.py
src/solana-mev-agent-py/oracles/helius.py
src/solana-mev-agent-py/oracles/pyth.py
src/solana-mev-agent-py/orders/__init__.py
src/solana-mev-agent-py/orders/batch.py
src/solana-mev-agent-py/orders/intent.py
src/solana-mev-agent-py/orders/quote.py
src/solana-mev-agent-py/orders/solution.py
src/solana-mev-agent-py/p2p/__init__.py
src/solana-mev-agent-py/p2p/level_one.py
src/solana-mev-agent-py/protocol_server/_server.py
src/solana-mev-agent-py/protocol_server/server.log
src/solana-mev-agent-py/protocol_server/static/background.png
src/solana-mev-agent-py/protocol_server/templates/batches.html
src/solana-mev-agent-py/protocol_server/templates/index.html
src/solana-mev-agent-py/protocol_server/templates/solutions.html
src/solana-mev-agent-py/protocol_server/utils/__init__.py
src/solana-mev-agent-py/protocol_server/utils/file_operations.py
src/solana-mev-agent-py/protocol_server/utils/server_utils.py
src/solana-mev-agent-py/sol/__init__.py
src/solana-mev-agent-py/sol/accounts.py
src/solana-mev-agent-py/sol/base.py
src/solana-mev-agent-py/sol/blocks.py
src/solana-mev-agent-py/sol/transactions.py
src/solana-mev-agent-py/utils/__init__.py
src/solana-mev-agent-py/utils/config.py
src/solana-mev-agent-py/utils/logging.py
src/solana-mev-agent-py/utils/maths.py
src/solana-mev-agent-py/utils/network.py
src/solana-mev-agent-py/utils/system.py
solana_mev_agent_py-0.1.0.dist-info/METADATA
solana_mev_agent_py-0.1.0.dist-info/WHEEL
solana_mev_agent_py-0.1.0.dist-info/entry_points.txt
solana_mev_agent_py-0.1.0.dist-info/RECORD
