Metadata-Version: 2.3
Name: solana-mev-agent-py
Version: 0.1.0
Summary: Aleph is Urani's Python in-house MEV agent, designed to take advantage of MEV opportunities on the Solana Blockchain through the Urani Protocol.
License: GPL-3.0 license
Author: Urani Labs
Requires-Python: >=3.10,<4.0
Classifier: License :: Other/Proprietary License
Classifier: Programming Language :: Python :: 3
Classifier: Programming Language :: Python :: 3.10
Classifier: Programming Language :: Python :: 3.11
Classifier: Programming Language :: Python :: 3.12
Classifier: Programming Language :: Python :: 3.13
Requires-Dist: apscheduler (>=3.10,<4.0)
Requires-Dist: base58 (>=2.1,<3.0)
Requires-Dist: beautifulsoup4 (>=4.12.2,<5.0.0)
Requires-Dist: fastapi (>=0.112.0,<0.113.0)
Requires-Dist: httpx (>=0.27,<0.28)
Requires-Dist: jinja2 (>=3.1.2,<4.0.0)
Requires-Dist: pythclient (==0.1.24)
Requires-Dist: python-dotenv
Requires-Dist: requests (>=2.32,<3.0)
Requires-Dist: scipy (>=1.14,<2.0)
Requires-Dist: semantic-types (>=0.1.5,<0.2.0)
Requires-Dist: solana (>=0.34,<0.35)
Requires-Dist: solders (>=0.21,<0.22)
Requires-Dist: ujson (>=5.0,<6.0)
Requires-Dist: uvicorn (>=0.30.6,<0.31.0)
